rcpicar/__init__.py
rcpicar/argument.py
rcpicar/clock.py
rcpicar/constants.py
rcpicar/message.py
rcpicar/process.py
rcpicar/py.typed
rcpicar/queue_.py
rcpicar/receive.py
rcpicar/reliable.py
rcpicar/send.py
rcpicar/service.py
rcpicar/socket_.py
rcpicar/unreliable.py
rcpicar/car/CarClientService.py
rcpicar/car/CarMessage.py
rcpicar/car/CarServerService.py
rcpicar/car/NetworkStatisticsMessage.py
rcpicar/car/__init__.py
rcpicar/client/Client.py
rcpicar/client/ClientArguments.py
rcpicar/client/__init__.py
rcpicar/discovery/DiscoveryClientService.py
rcpicar/discovery/DiscoveryCommonArguments.py
rcpicar/discovery/DiscoveryRequestMessage.py
rcpicar/discovery/DiscoveryResponseMessage.py
rcpicar/discovery/DiscoveryServerService.py
rcpicar/discovery/__init__.py
rcpicar/discovery/interfaces.py
rcpicar/expire/ExpireMessage.py
rcpicar/expire/ExpireReceiveService.py
rcpicar/expire/ExpireSendService.py
rcpicar/expire/IExpireReceiveListener.py
rcpicar/expire/__init__.py
rcpicar/expire/interfaces.py
rcpicar/gpio/GpioServerService.py
rcpicar/gpio/IGpio.py
rcpicar/gpio/IGpioServerService.py
rcpicar/gpio/PiGpio.py
rcpicar/gpio/__init__.py
rcpicar/gpio/interfaces.py
rcpicar/gstreamer/GStreamerClientService.py
rcpicar/gstreamer/GStreamerRequestMessage.py
rcpicar/gstreamer/GStreamerResponseMessage.py
rcpicar/gstreamer/GStreamerServerService.py
rcpicar/gstreamer/GStreamerVideoListener.py
rcpicar/gstreamer/VideoRequestMessage.py
rcpicar/gstreamer/VideoResponseMessage.py
rcpicar/gstreamer/VideoSettings.py
rcpicar/gstreamer/__init__.py
rcpicar/gstreamer/interfaces.py
rcpicar/latency/ILatencyListener.py
rcpicar/latency/ILatencyServerService.py
rcpicar/latency/LatencyClientService.py
rcpicar/latency/LatencyMessage.py
rcpicar/latency/LatencyServerService.py
rcpicar/latency/__init__.py
rcpicar/latency/interfaces.py
rcpicar/log/LogArguments.py
rcpicar/log/LogLevel.py
rcpicar/log/LogListener.py
rcpicar/log/__init__.py
rcpicar/log/util.py
rcpicar/priority/PriorityMessage.py
rcpicar-0.0.2.dist-info/LICENSE
rcpicar-0.0.2.dist-info/METADATA
rcpicar-0.0.2.dist-info/WHEEL
rcpicar-0.0.2.dist-info/top_level.txt
rcpicar-0.0.2.dist-info/RECORD
